{
	"partitions" : [
		{
			"name" : "Top",
			"pins" : [
				{
					"name" : "successFlag",
					"strict" : false
				},
				{
					"name" : "Units_seg[6]",
					"strict" : false
				},
				{
					"name" : "Units_seg[5]",
					"strict" : false
				},
				{
					"name" : "Units_seg[4]",
					"strict" : false
				},
				{
					"name" : "Units_seg[3]",
					"strict" : false
				},
				{
					"name" : "Units_seg[2]",
					"strict" : false
				},
				{
					"name" : "Units_seg[1]",
					"strict" : false
				},
				{
					"name" : "Units_seg[0]",
					"strict" : false
				},
				{
					"name" : "Tens_seg[6]",
					"strict" : false
				},
				{
					"name" : "Tens_seg[5]",
					"strict" : false
				},
				{
					"name" : "Tens_seg[4]",
					"strict" : false
				},
				{
					"name" : "Tens_seg[3]",
					"strict" : false
				},
				{
					"name" : "Tens_seg[2]",
					"strict" : false
				},
				{
					"name" : "Tens_seg[1]",
					"strict" : false
				},
				{
					"name" : "Tens_seg[0]",
					"strict" : false
				},
				{
					"name" : "Hunds_seg[6]",
					"strict" : false
				},
				{
					"name" : "Hunds_seg[5]",
					"strict" : false
				},
				{
					"name" : "Hunds_seg[4]",
					"strict" : false
				},
				{
					"name" : "Hunds_seg[3]",
					"strict" : false
				},
				{
					"name" : "Hunds_seg[2]",
					"strict" : false
				},
				{
					"name" : "Hunds_seg[1]",
					"strict" : false
				},
				{
					"name" : "Hunds_seg[0]",
					"strict" : false
				},
				{
					"name" : "reset",
					"strict" : false
				},
				{
					"name" : "enable",
					"strict" : false
				},
				{
					"name" : "clk",
					"strict" : false
				}
			]
		}
	]
}